AUTHORS.rst
CHANGELOG.md
CONTRIBUTING.rst
LICENSE
README.rst
countries_plus/.DS_Store
countries_plus/__init__.py
countries_plus/admin.py
countries_plus/apps.py
countries_plus/context_processors.py
countries_plus/fixtures/.DS_Store
countries_plus/fixtures/countries_data.json.gz
countries_plus/management/__init__.py
countries_plus/management/commands/__init__.py
countries_plus/management/commands/update_countries_plus.py
countries_plus/middleware.py
countries_plus/migrations/0001_initial.py
countries_plus/migrations/0002_auto_20150120_2225.py
countries_plus/migrations/0003_auto_20150611_1446.py
countries_plus/migrations/0004_auto_20150616_1242.py
countries_plus/migrations/0005_auto_20160224_1804.py
countries_plus/migrations/__init__.py
countries_plus/models.py
countries_plus/utils.py
django_countries_plus-2.1.0.dist-info/LICENSE
django_countries_plus-2.1.0.dist-info/WHEEL
django_countries_plus-2.1.0.dist-info/METADATA
django_countries_plus-2.1.0.dist-info/RECORD
