Metadata-Version: 2.1
Name: django-countries-plus
Version: 2.1.0
Summary: A django model & fixture containing all data from the countries table of Geonames.org
Home-page: https://github.com/cordery/django-countries-plus
License: MIT
Keywords: django-countries-plus
Author: Andrew Cordery
Author-email: cordery@gmail.com
Requires-Python: >=3.7,<4
Classifier: Development Status :: 5 - Production/Stable
Classifier: Framework :: Django
Classifier: Framework :: Django :: 2.2
Classifier: Framework :: Django :: 3.0
Classifier: Framework :: Django :: 4.0
Classifier: Intended Audience :: Developers
Classifier: License :: OSI Approved :: MIT License
Classifier: Natural Language :: English
Classifier: Programming Language :: Python :: 3
Classifier: Programming Language :: Python :: 3.10
Classifier: Programming Language :: Python :: 3.7
Classifier: Programming Language :: Python :: 3.8
Classifier: Programming Language :: Python :: 3.9
Requires-Dist: django (>=2.2)
Requires-Dist: requests (>=2,<3)
Requires-Dist: urllib3 (>=1.26,<2.0); python_version >= "3.10" and python_version < "4.0"
Project-URL: Repository, https://github.com/cordery/django-countries-plus
